{
  "interlocutores": [
    {
      "id": "auditor_eps",
      "tipo": "auditor",
      "nombre": "Auditor médico de EPS",
      "tiempo_min": 5,
      "objeciones_tipicas": ["no financiado con la UPC", "hay alternativa en el PBS", "falta justificación del caso particular", "no se agotaron alternativas"]
    },
    {
      "id": "paciente_dudoso",
      "tipo": "paciente",
      "nombre": "Paciente con dudas",
      "tiempo_min": 5,
      "objeciones_tipicas": ["¿por qué este y no el de siempre?", "¿es muy caro?", "leí que tiene efectos secundarios", "¿es seguro siendo nuevo?"]
    },
    {
      "id": "institucion",
      "tipo": "institucion",
      "nombre": "Comité de Farmacia / IPS",
      "tiempo_min": 7,
      "objeciones_tipicas": [
        "¿cuál es el costo por paciente vs. la alternativa del formulario?",
        "¿hay estudios head-to-head con el medicamento que ya usamos?",
        "¿aplica para el perfil epidemiológico de nuestra institución?",
        "¿cuál es el NNT reportado en el estudio pivotal?"
      ]
    }
  ]
}
